easyaiapi/__init__.py
easyaiapi/model_endpoint.py
easyaiapi/utils.py
easyaiapi/client/__init__.py
easyaiapi/client/client.py
easyaiapi/client/source.py
easyaiapi/server/__init__.py
easyaiapi/server/server.py
easyaiapi/server/wss.py
easyaiapi-0.0.7.dist-info/LICENSE
easyaiapi-0.0.7.dist-info/METADATA
easyaiapi-0.0.7.dist-info/WHEEL
easyaiapi-0.0.7.dist-info/top_level.txt
easyaiapi-0.0.7.dist-info/RECORD
