Metadata-Version: 2.1
Name: easyaiapi
Version: 0.0.7
Summary: Quickly deploy AI models using http or Websockets
Author: Olivier
Author-email: luowensheng2018@gmail.com
Keywords: python,api,websocket,AI
Classifier: Development Status :: 1 - Planning
Classifier: Intended Audience :: Developers
Classifier: Programming Language :: Python :: 3
Classifier: Operating System :: Unix
Classifier: Operating System :: MacOS :: MacOS X
Classifier: Operating System :: Microsoft :: Windows
License-File: LICENSE
Requires-Dist: opencv-stream
Requires-Dist: opencv-python
Requires-Dist: uvicorn[standard]
Requires-Dist: fastapi
Requires-Dist: requests
Requires-Dist: pillow
